TUNA/TUNA Manual.pdf
TUNA/__init__.py
TUNA/tuna.bat
TUNA/tuna.py
TUNA/tuna_basis.py
TUNA/tuna_cc.py
TUNA/tuna_ci.py
TUNA/tuna_dft.py
TUNA/tuna_energy.py
TUNA/tuna_md.py
TUNA/tuna_molecule.py
TUNA/tuna_mp.py
TUNA/tuna_optfreq.py
TUNA/tuna_out.py
TUNA/tuna_postscf.py
TUNA/tuna_scf.py
TUNA/tuna_thermo.py
TUNA/tuna_util.py
TUNA/tuna_integrals/__init__.py
TUNA/tuna_integrals/setup.py
TUNA/tuna_integrals/tuna_integral.c
TUNA/tuna_integrals/tuna_integral.cpython-314t-x86_64-linux-musl.so
quantumtuna-0.9.0.dist-info/METADATA
quantumtuna-0.9.0.dist-info/WHEEL
quantumtuna-0.9.0.dist-info/top_level.txt
quantumtuna-0.9.0.dist-info/RECORD
quantumtuna-0.9.0.dist-info/licenses/LICENSE
