Metadata-Version: 2.4
Name: QuantumTUNA
Version: 0.9.0
Summary: A user-friendly quantum chemistry program for diatomics.
Author-email: Harry Brough <harry.brough@icloud.com>
License-Expression: MIT
Project-URL: Repository, https://github.com/h-brough/TUNA
Project-URL: Documentation, https://github.com/h-brough/TUNA/blob/main/TUNA%20Manual.pdf
Project-URL: Changelog, https://github.com/h-brough/TUNA/blob/main/CHANGELOG.md
Keywords: quantum chemistry,molecular physics,hartree-fock,mp2,dft,coupled cluster,theoretical chemistry,computational chemistry,molecular modeling
Classifier: Development Status :: 4 - Beta
Classifier: Operating System :: Microsoft :: Windows
Classifier: Operating System :: MacOS
Classifier: Operating System :: Unix
Classifier: Programming Language :: Python
Classifier: Programming Language :: Cython
Classifier: Programming Language :: Python :: 3 :: Only
Classifier: Programming Language :: Python :: 3.12
Classifier: Programming Language :: Python :: 3.13
Classifier: Programming Language :: Python :: 3.14
Classifier: Intended Audience :: Science/Research
Classifier: Intended Audience :: Education
Classifier: Topic :: Scientific/Engineering
Requires-Python: >=3.12
License-File: LICENSE
Requires-Dist: numpy
Requires-Dist: scipy
Requires-Dist: matplotlib
Requires-Dist: termcolor
Dynamic: license-file
